src/data_treatment/__init__.py
src/data_treatment/data_pre_processing/__init__.py
src/data_treatment/data_pre_processing/concatenate_columns.py
src/index.py
src/parser/__init__.py
src/parser/feature_engineering/__init__.py
src/parser/feature_engineering/parser.py
src/parser/generator.py
src/parser/initial/__init__.py
src/parser/initial/parser.py
src/parser/initial/tests/__init__.py
src/parser/initial/tests/mock/ymal_mock.yaml
src/parser/initial/tests/mock/ymal_mock_fail.yaml
src/parser/initial/tests/parser_test.py
src/parser/tests/__init__.py
src/parser/tests/generator_test.py
src/parser/tests/mock/data_mock.csv
src/parser/tests/mock/first_case/ymal_mock.yaml
src/parser/tests/mock/second_case/ymal_mock.yaml
src/parser/tests/mock/third_case/ymal_mock.yaml
src/yamls/basic_example.yaml
pda_fga_playground-0.1.0.dist-info/LICENSE
pda_fga_playground-0.1.0.dist-info/WHEEL
pda_fga_playground-0.1.0.dist-info/METADATA
pda_fga_playground-0.1.0.dist-info/RECORD
